whatever/__init__.py
whatever/callables.py
whatever/chain.py
whatever/class_maker.py
whatever/dispatch.py
whatever/magic.py
whatever_forever-0.0.15.dist-info/DESCRIPTION.rst
whatever_forever-0.0.15.dist-info/METADATA
whatever_forever-0.0.15.dist-info/RECORD
whatever_forever-0.0.15.dist-info/WHEEL
whatever_forever-0.0.15.dist-info/metadata.json
whatever_forever-0.0.15.dist-info/top_level.txt
