Metadata-Version: 2.0
Name: whatever-forever
Version: 0.0.15
Summary: prototype whatever in the Jupyter notebook
Home-page: http://github.com/tonyfast/whatever-forever
Author: Tony Fast
Author-email: tony.fast@gmail.com
License: BSD-3-Clause
Keywords: IPython Magic Jupyter
Platform: UNKNOWN
Classifier: Topic :: Utilities
Classifier: Framework :: IPython
Classifier: Natural Language :: English
Classifier: Programming Language :: Python
Classifier: Intended Audience :: Developers
Classifier: Development Status :: 3 - Alpha
Classifier: Operating System :: OS Independent
Classifier: Programming Language :: Python :: 3
Classifier: License :: OSI Approved :: BSD License
Classifier: Topic :: Software Development :: Testing
Requires-Dist: toolz
